pydantic_graph/persistance/redis/__init__.py
pydantic_graph_persistance_redis-0.8.1.dist-info/METADATA
pydantic_graph_persistance_redis-0.8.1.dist-info/WHEEL
pydantic_graph_persistance_redis-0.8.1.dist-info/licenses/LICENSE
pydantic_graph_persistance_redis-0.8.1.dist-info/RECORD
