Metadata-Version: 2.4
Name: pydantic-graph-persistance-redis
Version: 0.8.1
Summary: State persistance using Redis as backend
Author-email: Félix Voituret <fvoituret@opsie.dev>
License-File: LICENSE
Keywords: agents,ai,pydantic,pydantic_graph,redis,redis-client,vector-database
Classifier: License :: OSI Approved :: MIT License
Classifier: Programming Language :: Python :: 3.11
Classifier: Programming Language :: Python :: 3.12
Classifier: Programming Language :: Python :: 3.13
Requires-Python: >=3.13
Requires-Dist: pydantic-graph>=0.8.1
Requires-Dist: redis>=6.4.0
